harvester/__init__.py
harvester/_version.py
harvester/models.py
harvester/user_agents.py
harvester/utils.py
harvester-0.5.2.dist-info/LICENSE
harvester-0.5.2.dist-info/METADATA
harvester-0.5.2.dist-info/WHEEL
harvester-0.5.2.dist-info/top_level.txt
harvester-0.5.2.dist-info/RECORD
